snakebar.py
snakebar-0.1.1.dist-info/METADATA
snakebar-0.1.1.dist-info/WHEEL
snakebar-0.1.1.dist-info/entry_points.txt
snakebar-0.1.1.dist-info/top_level.txt
snakebar-0.1.1.dist-info/RECORD
