Metadata-Version: 2.4
Name: snakebar
Version: 0.1.1
Summary: A tqdm-like progress bar that snakes across your terminal via a random space-filling curve.
Author: Majo Bustamante Rosell
License: MIT
Project-URL: Homepage, https://github.com/majoburo/snakebar
Project-URL: Repository, https://github.com/majoburo/snakebar
Requires-Python: >=3.9
